Cargo.toml
LICENSE
MANIFEST.in
README.md
pyproject.toml
setup.py
pylevel/__init__.py
pylevel.egg-info/PKG-INFO
pylevel.egg-info/SOURCES.txt
pylevel.egg-info/dependency_links.txt
pylevel.egg-info/not-zip-safe
pylevel.egg-info/top_level.txt
src/lib.rs