Metadata-Version: 2.1
Name: pylevel
Version: 0.1.0
Summary: A LevelDB driver
Home-page: http://github.com/nakagami/pylevel/
Author: Hajime Nakagami
Author-email: nakagami@gmail.com
License: MIT
Keywords: LevelDB
Platform: UNKNOWN
Classifier: License :: OSI Approved :: MIT License
Classifier: Development Status :: 4 - Beta
Classifier: Intended Audience :: Developers
Classifier: Programming Language :: Python
Classifier: Programming Language :: Python :: 3.8
Classifier: Programming Language :: Python :: 3.9
Classifier: Programming Language :: Rust
Classifier: Operating System :: POSIX
License-File: LICENSE
